Spring232KaifaJianmingJiaochengZhangyong/README.md
Spring232KaifaJianmingJiaochengZhangyong/__init__.py
Spring232KaifaJianmingJiaochengZhangyong/__main__.py
Spring232KaifaJianmingJiaochengZhangyong/file.pdf
Spring232KaifaJianmingJiaochengZhangyong/index.html
spring_2_3_2_kaifa_jianming_jiaocheng_zhangyong-2024.3.2.0.dist-info/METADATA
spring_2_3_2_kaifa_jianming_jiaocheng_zhangyong-2024.3.2.0.dist-info/WHEEL
spring_2_3_2_kaifa_jianming_jiaocheng_zhangyong-2024.3.2.0.dist-info/entry_points.txt
spring_2_3_2_kaifa_jianming_jiaocheng_zhangyong-2024.3.2.0.dist-info/top_level.txt
spring_2_3_2_kaifa_jianming_jiaocheng_zhangyong-2024.3.2.0.dist-info/RECORD
